{"useInstanceRenderData":true,"name":"bcm_props_utah_1","scale":[1,1,1],"class":"TSStatic","shapeName":"/levels/west_coast_usa/art/shapes/objects/s_toll_booth_center.dae","position":[-827.41772460938,-35.52880859375,293.30001831055],"rotationMatrix":[0.4226182617407,0.90630778703665,0,-0.90630778703665,0.4226182617407,0,0,0,1],"persistentId":"bcm-props-1776872767-8361"}
{"useInstanceRenderData":true,"name":"bcm_props_utah_2","scale":[1,1,1],"class":"TSStatic","shapeName":"/levels/west_coast_usa/art/shapes/objects/s_toll_booth_center.dae","position":[-827.19458007813,-36.57727432251,293.30001831055],"rotationMatrix":[-0.4067366430758,-0.9135454576426,0,0.9135454576426,-0.4067366430758,0,0,0,1],"persistentId":"bcm-props-1776872832-7896"}
{"useInstanceRenderData":true,"name":"bcm_props_utah_3","scale":[1,1,1],"class":"TSStatic","shapeName":"/levels/utah/art/shapes/buildings/ut_bridge_destroyed.dae","position":[-930.87445068359,10.013820648193,293.30001831055],"rotationMatrix":[0.4067366430758,0.9135454576426,0,-0.9135454576426,0.4067366430758,0,0,0,1],"persistentId":"bcm-props-1776875943-9367"}
{"useInstanceRenderData":true,"name":"bcm_props_utah_4","scale":[1,1,1],"class":"TSStatic","shapeName":"/levels/west_coast_usa/art/shapes/objects/s_toll_booth_center.dae","position":[-278.51190185547,-890.54931640625,131.42614746094],"rotationMatrix":[0.017452406437284,0.99984769515639,0,-0.99984769515639,0.017452406437284,0,0,0,1],"persistentId":"bcm-props-1776880712-9524"}
