{"rotation":[0,0,0.00081680819741905,0.99999966641213],"name":"East Coast Tiny Port","center":[-69.094459533691,-867.15368652344,14.117603242397],"nodeType":"road","type":"travelNode","triggerSize":[8,8,4],"id":"ec_travel_1","connections":[{"toll":0,"targetNode":"it_port1","connectionType":"ship","targetMap":"italy"}]}
{"rotation":[0,0,0.93744331263651,-0.34813795482981],"name":"East Coast Last Stop","center":[-787.45550537109,504.50402832031,23.459470689297],"nodeType":"road","type":"travelNode","triggerSize":[8,8,4],"id":"ec_travel_2","connections":[{"toll":200,"targetNode":"utah_road_3","connectionType":"road","targetMap":"utah"}]}
